tranception_pytorch/__init__.py
tranception_pytorch/tranception_pytorch.py
tranception_pytorch-0.0.8.dist-info/LICENSE
tranception_pytorch-0.0.8.dist-info/METADATA
tranception_pytorch-0.0.8.dist-info/WHEEL
tranception_pytorch-0.0.8.dist-info/top_level.txt
tranception_pytorch-0.0.8.dist-info/RECORD
